caggpu/__init__.py
caggpu/nvidia_cuda.py
caggpu-0.0.2.dist-info/LICENSE
caggpu-0.0.2.dist-info/METADATA
caggpu-0.0.2.dist-info/WHEEL
caggpu-0.0.2.dist-info/top_level.txt
caggpu-0.0.2.dist-info/RECORD
