Metadata-Version: 2.1
Name: caggpu
Version: 0.0.2
Summary: A GPU utility package for Coargus services.
Author-email: "minkyu.choi" <minkyu.choi07@gmail.com>
License: MIT License
Project-URL: homepage, https://github.com/Coargus/utility-pkg-gpu/
Project-URL: documentation, https://github.com/Coargus/utility-pkg-gpu/docs
Project-URL: repository, https://github.com/Coargus/utility-pkg-gpu/
Requires-Python: >=3.8
License-File: LICENSE
Requires-Dist: pynvml
Provides-Extra: dev
Requires-Dist: black ; extra == 'dev'
Requires-Dist: flake8 ; extra == 'dev'
Requires-Dist: mypy ; extra == 'dev'
Provides-Extra: test
Requires-Dist: pytest >=6.0 ; extra == 'test'
Requires-Dist: pytest-cov ; extra == 'test'
